interactions/ext/fastapi/__init__.py
interactions/ext/fastapi/main.py
interactions_fastapi-0.0.1.dist-info/LICENSE
interactions_fastapi-0.0.1.dist-info/METADATA
interactions_fastapi-0.0.1.dist-info/WHEEL
interactions_fastapi-0.0.1.dist-info/top_level.txt
interactions_fastapi-0.0.1.dist-info/RECORD
